GridCalEngine/__init__.py
GridCalEngine/__version__.py
GridCalEngine/api.py
GridCalEngine/basic_structures.py
GridCalEngine/data_logger.py
GridCalEngine/grid_analysis.py
GridCalEngine/setup.py
GridCalEngine.egg-info/PKG-INFO
GridCalEngine.egg-info/SOURCES.txt
GridCalEngine.egg-info/dependency_links.txt
GridCalEngine.egg-info/requires.txt
GridCalEngine.egg-info/top_level.txt
GridCalEngine/Core/__init__.py
GridCalEngine/Core/admittance_matrices.py
GridCalEngine/Core/topology.py
GridCalEngine/Core/Compilers/__init__.py
GridCalEngine/Core/Compilers/circuit_to_bentayga.py
GridCalEngine/Core/Compilers/circuit_to_data.py
GridCalEngine/Core/Compilers/circuit_to_newton_pa.py
GridCalEngine/Core/Compilers/circuit_to_optimods.py
GridCalEngine/Core/Compilers/circuit_to_pgm.py
GridCalEngine/Core/DataStructures/__init__.py
GridCalEngine/Core/DataStructures/battery_data.py
GridCalEngine/Core/DataStructures/branch_data.py
GridCalEngine/Core/DataStructures/bus_data.py
GridCalEngine/Core/DataStructures/generator_data.py
GridCalEngine/Core/DataStructures/hvdc_data.py
GridCalEngine/Core/DataStructures/load_data.py
GridCalEngine/Core/DataStructures/numerical_circuit.py
GridCalEngine/Core/DataStructures/shunt_data.py
GridCalEngine/Core/Devices/__init__.py
GridCalEngine/Core/Devices/editable_device.py
GridCalEngine/Core/Devices/enumerations.py
GridCalEngine/Core/Devices/measurement.py
GridCalEngine/Core/Devices/multi_circuit.py
GridCalEngine/Core/Devices/templates.py
GridCalEngine/Core/Devices/Aggregation/__init__.py
GridCalEngine/Core/Devices/Aggregation/area.py
GridCalEngine/Core/Devices/Aggregation/contingency.py
GridCalEngine/Core/Devices/Aggregation/contingency_group.py
GridCalEngine/Core/Devices/Aggregation/country.py
GridCalEngine/Core/Devices/Aggregation/emission_gas.py
GridCalEngine/Core/Devices/Aggregation/fuel.py
GridCalEngine/Core/Devices/Aggregation/investment.py
GridCalEngine/Core/Devices/Aggregation/investments_group.py
GridCalEngine/Core/Devices/Aggregation/technology.py
GridCalEngine/Core/Devices/Aggregation/zone.py
GridCalEngine/Core/Devices/Associations/__init__.py
GridCalEngine/Core/Devices/Associations/generator_emission.py
