Metadata-Version: 2.1
Name: GridCalEngine
Version: 5.0.0a2
Summary: GridCal is a Power Systems simulation program intended for professional use and research
Home-page: https://github.com/SanPen/GridCal
Author: Santiago Peñate Vera et. Al.
Author-email: santiago@gridcal.org
License: LGPL
Keywords: power systems planning
Platform: UNKNOWN
Classifier: License :: OSI Approved :: GNU Library or Lesser General Public License (LGPL)
Classifier: Programming Language :: Python :: 3.10
Requires-Python: >=3.6
Provides-Extra: gch5 files
